[
  {
    "id": "aubrac",
    "nom": "Lucie Aubrac",
    "annee": 1943,
    "ville": "Lyon",
    "url": "./lucieAUBRAC.html",
    "vignette": "./aubrac.jpeg",
    "tags": ["résistance","lyon","évasion"]
  },
  {
    "id": "albrecht",
    "nom": "Berty Albrecht",
    "annee": 1943,
    "ville": "Paris",
    "url": "./bertyALBRECHT.html",
    "vignette": "./albrecht.jpg",
    "tags": ["combat","solidarité"]
  },
  {
    "id": "baker",
    "nom": "Joséphine Baker",
    "annee": 1942,
    "ville": "Paris",
    "url": "./josephineBAKER.html",
    "vignette": "./baker.jpg",
    "tags": ["renseignement","artiste"]
  }
]
